ixbrlparse/__about__.py
ixbrlparse/__init__.py
ixbrlparse/__main__.py
ixbrlparse/core.py
ixbrlparse/hookspecs.py
ixbrlparse/plugins.py
ixbrlparse/py.typed
ixbrlparse/cli/__init__.py
ixbrlparse/components/__init__.py
ixbrlparse/components/_base.py
ixbrlparse/components/constants.py
ixbrlparse/components/context.py
ixbrlparse/components/formats.py
ixbrlparse/components/nonnumeric.py
ixbrlparse/components/numeric.py
ixbrlparse/components/transform.py
ixbrlparse-0.11.2.dist-info/METADATA
ixbrlparse-0.11.2.dist-info/WHEEL
ixbrlparse-0.11.2.dist-info/entry_points.txt
ixbrlparse-0.11.2.dist-info/licenses/LICENSE
ixbrlparse-0.11.2.dist-info/RECORD
