Metadata-Version: 2.4
Name: ixbrlparse
Version: 0.11.2
Summary: A python module for getting useful data out of ixbrl files.
Project-URL: Homepage, https://github.com/kanedata/ixbrl-parse
Project-URL: Documentation, https://ixbrl-parse.readthedocs.io/
Project-URL: Issues, https://github.com/kanedata/ixbrl-parse/issues
Project-URL: Source, https://github.com/kanedata/ixbrl-parse
Author-email: David Kane <david@dkane.net>
License-Expression: MIT
License-File: LICENSE
Classifier: Development Status :: 4 - Beta
Classifier: License :: OSI Approved :: MIT License
Classifier: Operating System :: OS Independent
Classifier: Programming Language :: Python :: 3 :: Only
Classifier: Programming Language :: Python :: 3.10
Classifier: Programming Language :: Python :: 3.11
Classifier: Programming Language :: Python :: 3.12
Classifier: Programming Language :: Python :: 3.13
Classifier: Programming Language :: Python :: 3.14
Classifier: Topic :: Office/Business :: Financial :: Accounting
Classifier: Topic :: Text Processing :: Markup :: HTML
Classifier: Topic :: Text Processing :: Markup :: XML
Requires-Python: >=3.10
Requires-Dist: beautifulsoup4
Requires-Dist: click
Requires-Dist: lxml>=5.2.2
Requires-Dist: pluggy>=1
Requires-Dist: word2number
Provides-Extra: docs
Requires-Dist: mkdocs; extra == 'docs'
Requires-Dist: mkdocs-material; extra == 'docs'
Requires-Dist: mkdocstrings[python]; extra == 'docs'
Provides-Extra: lint
Requires-Dist: mypy>=1.0.0; extra == 'lint'
Requires-Dist: ruff>=0.4.7; extra == 'lint'
Requires-Dist: types-beautifulsoup4; extra == 'lint'
Requires-Dist: types-click; extra == 'lint'
Provides-Extra: test
Requires-Dist: coverage[toml]>=6.5; extra == 'test'
Requires-Dist: pytest; extra == 'test'
